langdag/__about__.py
langdag/__init__.py
langdag/core.py
langdag/decorator.py
langdag/error.py
langdag/executor.py
langdag/processor.py
langdag/runner.py
langdag/selector.py
langdag/utils.py
langdag/plugins/__init__.py
langdag/plugins/base.py
langdag/plugins/langfuse.py
langdag-0.2.0a0.dist-info/METADATA
langdag-0.2.0a0.dist-info/WHEEL
langdag-0.2.0a0.dist-info/licenses/LICENSE.txt
langdag-0.2.0a0.dist-info/RECORD
