Metadata-Version: 2.4
Name: langdag
Version: 0.2.0a0
Summary: LLM agent workflow orchestration with DAG
Project-URL: Homepage, https://github.com/reedxiao/langdag
Project-URL: Issues, https://github.com/reedxiao/langdag/issues
Author: Reed Xiao
License-Expression: MIT
License-File: LICENSE.txt
Classifier: Intended Audience :: Developers
Classifier: License :: OSI Approved :: MIT License
Classifier: Operating System :: OS Independent
Classifier: Programming Language :: Python :: 3
Classifier: Topic :: Software Development :: Libraries :: Python Modules
Requires-Python: >=3.8
Requires-Dist: dill~=0.3.8
Requires-Dist: paradag~=1.2.0
Requires-Dist: rich~=13.7.1
